searchdocs/__init__.py
searchdocs/__main__.py
searchdocs/py.typed
searchdocs-0.2.2.dist-info/LICENSE
searchdocs-0.2.2.dist-info/METADATA
searchdocs-0.2.2.dist-info/WHEEL
searchdocs-0.2.2.dist-info/entry_points.txt
searchdocs-0.2.2.dist-info/RECORD
