Metadata-Version: 2.1
Name: searchdocs
Version: 0.2.2
Summary: Search the Python documentation from your terminal.
Author-email: Dominic Davis-Foster <dominic@davis-foster.co.uk>
License: MIT
Keywords: documentation,search,terminal
Home-page: https://github.com/domdfcoding/searchdocs
Project-URL: Issue Tracker, https://github.com/domdfcoding/searchdocs/issues
Project-URL: Source Code, https://github.com/domdfcoding/searchdocs
Project-URL: Documentation, https://searchdocs.readthedocs.io/en/latest
Platform: Windows
Platform: macOS
Platform: Linux
Classifier: Development Status :: 4 - Beta
Classifier: Environment :: Console
Classifier: License :: OSI Approved :: MIT License
Classifier: Operating System :: OS Independent
Classifier: Programming Language :: Python
Classifier: Programming Language :: Python :: 3 :: Only
Classifier: Programming Language :: Python :: 3.7
Classifier: Programming Language :: Python :: 3.8
Classifier: Programming Language :: Python :: 3.9
Classifier: Programming Language :: Python :: 3.10
Classifier: Programming Language :: Python :: 3.11
Classifier: Programming Language :: Python :: 3.12
Classifier: Programming Language :: Python :: Implementation :: CPython
Classifier: Programming Language :: Python :: Implementation :: PyPy
Classifier: Topic :: Documentation
Classifier: Typing :: Typed
Requires-Python: >=3.7
Requires-Dist: apeye>=0.7.0
Requires-Dist: appdirs>=1.4.4
Requires-Dist: click>=7.1.2
Requires-Dist: consolekit>=1.1.1
Requires-Dist: diskcache>=5.1.0
Requires-Dist: domdf-python-tools>=2.6.0
Requires-Dist: fuzzywuzzy>=0.18.0
Requires-Dist: levenshtein>=0.12.0
Requires-Dist: sphobjinv>=2.0.1
Requires-Dist: typing-extensions>=3.7.4.3
